MANIFEST.in
README.md
setup.cfg
setup.py
pro_net_worker.egg-info/PKG-INFO
pro_net_worker.egg-info/SOURCES.txt
pro_net_worker.egg-info/dependency_links.txt
pro_net_worker.egg-info/requires.txt
pro_net_worker.egg-info/top_level.txt
pronet_worker/__init__.py
pronet_worker/worker.py
test/test_worker.py