Metadata-Version: 1.1
Name: pro-net-worker
Version: 1.0.0
Summary: A process pool to execute tasks and dynamic tasks.
Home-page: https://github.com/processgraph-net/pro-net-worker
Author: ProcessGraph.Net
Author-email: info@processgraph.net
License: UNKNOWN
Download-URL: https://github.com/processgraph-net/pro-net-worker/archive/v1.0.0.tar.gz
Keywords: ProcessGraph,Task,Worker,multiprocessing
Platform: UNKNOWN
Classifier: Programming Language :: Python
Classifier: Programming Language :: Python :: 3
Classifier: Development Status :: 4 - Beta
Classifier: Environment :: Other Environment
Classifier: Intended Audience :: Developers
Classifier: License :: OSI Approved :: MIT License
Classifier: Programming Language :: Python :: 3
Classifier: Programming Language :: Python :: 3.3
Classifier: Programming Language :: Python :: 3.4
Classifier: Programming Language :: Python :: 3.5
Classifier: Programming Language :: Python :: 3.6
Classifier: Programming Language :: Python :: 3.7
Classifier: Operating System :: OS Independent
Classifier: Topic :: Software Development :: Libraries :: Python Modules
